elixs/__init__.py
elixs/errorhandlers.py
elixs/load.py
elixs/logger.py
elixs/sqllogger.py
elixs/elixs/__init__.py
elixs/elixs/argparser.py
elixs/elixs/colors.py
elixs/elixs/errorhandlers.py
elixs/elixs/load.py
elixs/elixs/logger.py
elixs/elixs/sqllogger.py
elixs-0.1.3.dist-info/LICENSE.txt
elixs-0.1.3.dist-info/METADATA
elixs-0.1.3.dist-info/WHEEL
elixs-0.1.3.dist-info/top_level.txt
elixs-0.1.3.dist-info/RECORD
