Metadata-Version: 2.1
Name: elixs
Version: 0.1.3
Summary: Standart Library for elixs.dev
Home-page: UNKNOWN
Author: Elias Kremer
Author-email: eliservices.server@gmail.com
License: UNKNOWN
Platform: UNKNOWN
Classifier: Programming Language :: Python :: 3
Classifier: License :: OSI Approved :: GNU Affero General Public License v3
Classifier: Operating System :: POSIX :: Linux
Requires-Python: >=3.10
License-File: LICENSE.txt
Requires-Dist: color4console
Requires-Dist: mysql-connector-python
